pygpas/__init__.py
pygpas-0.0.1.dist-info/METADATA
pygpas-0.0.1.dist-info/WHEEL
pygpas-0.0.1.dist-info/RECORD
